otter/__init__.py
otter/__main__.py
otter/api.py
otter/assign/__init__.py
otter/assign/assignment.py
otter/assign/blocks.py
otter/assign/cell_factory.py
otter/assign/feature_toggle.py
otter/assign/notebook_transformer.py
otter/assign/output.py
otter/assign/plugins.py
otter/assign/question_config.py
otter/assign/r_adapter/__init__.py
otter/assign/r_adapter/cell_factory.py
otter/assign/r_adapter/rmarkdown_converter.py
otter/assign/r_adapter/solutions.py
otter/assign/r_adapter/tests_manager.py
otter/assign/solutions.py
otter/assign/tests_manager.py
otter/assign/utils.py
otter/check/__init__.py
otter/check/logs.py
otter/check/notebook.py
otter/check/utils.py
otter/check/validate_export/__init__.py
otter/check/validate_export/__main__.py
otter/cli.py
otter/execute/__init__.py
otter/execute/checker.py
otter/execute/logging.py
otter/execute/preprocessor.py
otter/export/__init__.py
otter/export/exporters/__init__.py
otter/export/exporters/base_exporter.py
otter/export/exporters/templates/via_html/conf.json
otter/export/exporters/templates/via_html/index.html.j2
otter/export/exporters/templates/via_latex/conf.json
otter/export/exporters/templates/via_latex/index.tex.j2
otter/export/exporters/templates/via_latex_xecjk/conf.json
otter/export/exporters/templates/via_latex_xecjk/index.tex.j2
otter/export/exporters/utils.py
otter/export/exporters/via_html.py
otter/export/exporters/via_latex.py
otter/generate/__init__.py
otter/generate/templates/common/run_autograder
otter/generate/templates/common/run_otter.py
otter/generate/templates/python/setup.sh
otter/generate/templates/r/setup.sh
otter/generate/token.py
otter/generate/utils.py
otter/grade/Dockerfile
otter/grade/__init__.py
otter/grade/containers.py
otter/grade/utils.py
otter/logging.py
otter/nbmeta_config.py
otter/plugins/__init__.py
otter/plugins/abstract_plugin.py
otter/plugins/builtin/__init__.py
otter/plugins/builtin/gmail_notifications/__init__.py
otter/plugins/builtin/gmail_notifications/bin/__init__.py
otter_grader-6.1.6.dist-info/METADATA
otter_grader-6.1.6.dist-info/WHEEL
otter_grader-6.1.6.dist-info/entry_points.txt
otter_grader-6.1.6.dist-info/licenses/LICENSE
otter_grader-6.1.6.dist-info/RECORD
