Metadata-Version: 2.4
Name: otter-grader
Version: 6.1.6
Summary: A Python and R autograding solution
License: BSD-3-Clause
License-File: LICENSE
Author: Christopher Pyles
Author-email: cpyles@berkeley.edu
Requires-Python: >=3.9,<4.0
Classifier: License :: OSI Approved :: BSD License
Classifier: Operating System :: OS Independent
Classifier: Programming Language :: Python :: 3
Classifier: Programming Language :: Python :: 3.9
Classifier: Programming Language :: Python :: 3.10
Classifier: Programming Language :: Python :: 3.11
Classifier: Programming Language :: Python :: 3.12
Classifier: Programming Language :: Python :: 3.13
Classifier: Programming Language :: Python :: 3.14
Provides-Extra: grading
Provides-Extra: plugins
Provides-Extra: r
Requires-Dist: click (>=8.1.7,<9.0.0)
Requires-Dist: dill (>=0.3.0)
Requires-Dist: fica (>=0.4.1)
Requires-Dist: google-api-python-client ; extra == "plugins"
Requires-Dist: google-auth-oauthlib ; extra == "plugins"
Requires-Dist: gspread ; extra == "plugins"
Requires-Dist: ipykernel ; extra == "grading"
Requires-Dist: ipylab (>=1.0.0,<2.0.0)
Requires-Dist: ipython
Requires-Dist: ipywidgets (>=8.1.5,<9.0.0)
Requires-Dist: jinja2 (>=3.1,<4.0)
Requires-Dist: jupyter_client ; extra == "grading"
Requires-Dist: jupytext (>=1.16.4,<2.0.0)
Requires-Dist: nbconvert[webpdf] (>=6.0.0) ; sys_platform != "emscripten" and sys_platform != "wasi"
Requires-Dist: nbformat (>=5.0.0)
Requires-Dist: pandas (>=2.0.0)
Requires-Dist: pypdf ; extra == "grading"
Requires-Dist: python-on-whales (>=0.72.0,<1.0.0)
Requires-Dist: pyyaml (>=6,<7)
Requires-Dist: requests (>=2.31,<3.0)
Requires-Dist: rpy2 (>=3.5.16,<4.0.0) ; extra == "r"
Requires-Dist: six ; extra == "plugins"
Requires-Dist: wrapt (>=1.16.0,<2.0.0)
Project-URL: Documentation, https://otter-grader.readthedocs.io/
Project-URL: Homepage, https://otter-grader.readthedocs.io/
Project-URL: Repository, https://github.com/ucbds-infra/otter-grader
